[{"name":"热门","city":["上海","南京","无锡","常州","苏州","扬州","镇江","泰州","杭州","宁波","温州","嘉州","湖州","绍兴","舟山","台州","丽水","芜湖","安庆","巢湖","池州","福州","厦门","南平","鹰潭","上饶","青岛","广州","深圳","江门","惠州","阳江","清远","阳西","黄山","吉林"]},
 {"name":"ABCD","city":["阿坝藏羌族自治州","安庆","澳门","百色","蚌埠","保定","保定","保山","北海","北京","毕节地区","滨州","沧州","常德","常州","长春","长沙","巢湖","成都","承德","池州","赤峰","滁州","大理白族自治州","大连","大庆","德州","东营","东莞"]},
 {"name":"EFGH","city":["恩施土家苗族自治州","佛山","福州","福州","抚州","赣州","广州","贵阳","桂林","哈尔滨","海口","邯郸","汉中","杭州","合肥","河池","河源","菏泽","衡阳","呼和浩特","呼伦贝尔","湖州","葫芦岛","淮安","黄冈","黄山","黄石","惠州"]},
 {"name":"JKLM","city":["吉安","吉林","济南","济宁","嘉兴","江门","金华","晋中","荆门","荆州","九江","开封","昆明","拉萨","兰州","廊坊","乐山","丽江","丽水","连云港","临汾","临沂","柳州","陇南","洛阳","绵阳","牡丹江"]},
 {"name":"NOPQRS","city":["南昌","南充","南京","南平","南通","南阳","宁波","宁德","齐齐哈尔","黔东南苗族侗族自治州","秦皇岛","青岛","清远","衢州","日照","三明","三亚","上海","上饶","韶关","绍兴","深圳","沈阳","石家庄","苏州","绥化"]},
 {"name":"TUVWX","city":["台州","太原","泰安","泰州","唐山","台湾","铜仁地区","威海","淮坊","渭南","温州","乌兰擦布","乌鲁木齐","无锡","芜湖","武汉","西安","西宁","西双版纳傣族自治州","锡林郭勒盟","厦门","咸宁","湘西土家族苗族自治州","襄樊","孝感","新乡","邢台","徐州","香港"]},
 {"name":"YZ","city":["雅安","烟台","延安","延边朝鲜族自治州","盐城","扬州","阳江","阳西","宜昌","宜春","银川","营口","榆林","岳阳","运城","湛江","张家界","张家口","漳州","肇庆","镇江","郑州","中山","舟山","珠海","淄博","遵义"]}

]